{
    "games": [
        [
            "Red",
            "Blue",
            "RANDOM15421385",
            0,
            null,
            73.0,
            0
        ],
        [
            "Red",
            "Blue",
            "RANDOM35594194",
            7,
            "Red",
            73.0,
            0
        ],
        [
            "Red",
            "Blue",
            "RANDOM85849387",
            30,
            "Red",
            73.0,
            0
        ],
        [
            "Red",
            "Blue",
            "RANDOM28384095",
            30,
            "Red",
            73.0,
            0
        ],
        [
            "Red",
            "Blue",
            "RANDOM50951597",
            18,
            "Red",
            73.0,
            0
        ],
        [
            "Red",
            "Blue",
            "RANDOM63544409",
            14,
            "Red",
            73.0,
            0
        ],
        [
            "Red",
            "Blue",
            "RANDOM76350328",
            8,
            "Red",
            73.0,
            0
        ],
        [
            "Red",
            "Blue",
            "RANDOM51390453",
            12,
            "Red",
            73.0,
            0
        ],
        [
            "Red",
            "Blue",
            "RANDOM51625795",
            30,
            "Red",
            73.0,
            0
        ],
        [
            "Red",
            "Blue",
            "RANDOM26851578",
            0,
            null,
            73.0,
            0
        ],
        [
            "Red",
            "Blue",
            "RANDOM97896791",
            22,
            "Blue",
            73.0,
            0
        ],
        [
            "Red",
            "Blue",
            "RANDOM79451391",
            2,
            "Red",
            73.0,
            0
        ],
        [
            "Red",
            "Blue",
            "RANDOM89980147",
            4,
            "Red",
            73.0,
            0
        ],
        [
            "Red",
            "Blue",
            "RANDOM3104682",
            4,
            "Red",
            73.0,
            0
        ],
        [
            "Red",
            "Blue",
            "RANDOM31370906",
            1,
            "Red",
            73.0,
            0
        ],
        [
            "Red",
            "Blue",
            "RANDOM49329896",
            0,
            null,
            73.0,
            0
        ],
        [
            "Red",
            "Blue",
            "RANDOM65843343",
            21,
            "Red",
            73.0,
            0
        ],
        [
            "Red",
            "Blue",
            "RANDOM46148149",
            6,
            "Red",
            73.0,
            0
        ],
        [
            "Red",
            "Blue",
            "RANDOM98214693",
            25,
            "Red",
            73.0,
            0
        ],
        [
            "Red",
            "Blue",
            "RANDOM18835222",
            26,
            "Red",
            73.0,
            0
        ]
    ],
    "layouts": [
        "RANDOM15421385",
        "RANDOM35594194",
        "RANDOM85849387",
        "RANDOM28384095",
        "RANDOM50951597",
        "RANDOM63544409",
        "RANDOM76350328",
        "RANDOM51390453",
        "RANDOM51625795",
        "RANDOM26851578",
        "RANDOM97896791",
        "RANDOM79451391",
        "RANDOM89980147",
        "RANDOM3104682",
        "RANDOM31370906",
        "RANDOM49329896",
        "RANDOM65843343",
        "RANDOM46148149",
        "RANDOM98214693",
        "RANDOM18835222"
    ],
    "max_steps": 1200,
    "teams_stats": {
        "Blue": [
            10.0,
            6,
            1,
            3,
            16,
            0,
            22
        ],
        "Red": [
            85.0,
            51,
            16,
            3,
            1,
            0,
            238
        ]
    }
}